{
	"parent":"skyblock:quests/root",
	"display":{
		"icon":{
			"item":"minecraft:paper"
		},
		"title":"Charlie",
		"description":"Talk to the Charlie in the Birch Forest.",
		"frame":"task",
		"show_toast":true,
		"announce_to_chat":true,
		"hidden":false
	},
	"criteria":{
		"criterion":{
			"trigger":"minecraft:player_interacted_with_entity",
			"conditions":{
				"entity":{
					"nbt":"{Tags:[\"charlie\"]}"
				},
				"item":{
					"items":[
						"minecraft:birch_log"
					],
					"count":64
				},
				"player":[
					{
						"condition":"entity_properties",
						"entity":"this",
						"predicate":{
							"nbt":"{Tags:[\"timber\"]}"
						}
					}
				]
			}
		}
	},
	"rewards":{
		"function":"skyblock:npcs/charlie",
		"loot":[
			"minecraft:items/emerald",
			"minecraft:items/emerald",
			"minecraft:items/emerald",
			"minecraft:items/emerald",
			"minecraft:items/emerald",
			"minecraft:items/emerald",
			"minecraft:items/emerald",
			"minecraft:items/emerald",
			"minecraft:items/emerald",
			"minecraft:items/emerald",
			"minecraft:items/emerald",
			"minecraft:items/emerald",
			"minecraft:items/emerald",
			"minecraft:items/emerald",
			"minecraft:items/emerald",
			"minecraft:items/emerald"
		]
	}
}
