{
	"pools":[
		{
			"rolls":1,
			"entries":[
				{
					"type":"empty",
					"weight":55
				},
				{
					"type":"item",
					"name":"acacia_log",
					"weight":15
				},
				{
					"type":"item",
					"name":"spruce_log",
					"weight":15
				},
				{
					"type":"item",
					"name":"dark_oak_log",
					"weight":15
				}
			],
			"functions":[
				{
					"function":"looting_enchant",
					"count":{
						"min":0,
						"max":1
					}
				}
			]
		},
		{
			"rolls":1,
			"bonus_rolls":{
				"min":0.0,
				"max":1.0
			},
			"entries":[
				{
					"type":"empty",
					"weight":99970
				},
				{
					"type":"loot_table",
					"name":"skyblock:items/travel_scrolls/howling_cave",
					"weight":20,
					"quality":3
				},
				{
					"type":"loot_table",
					"name":"skyblock:items/pets/hound/epic",
					"weight":8,
					"quality":3
				},
				{
					"type":"loot_table",
					"name":"skyblock:items/pets/hound/legendary",
					"weight":2,
					"quality":4
				}
			]
		}
	]
}
