{
	"pools":[
		{
			"rolls":1,
			"entries":[
				{
					"type":"loot_table",
					"name":"skyblock:items/sea_creatures/crystal_hollows/flaming_worm",
					"quality":2,
					"weight":9091,
					"conditions":[
						{
							"condition":"location_check",
							"predicate":{
								"dimension":"skyblock:dwarven_mines"
							}
						}
					]
				},
				{
					"type":"loot_table",
					"name":"skyblock:items/sea_creatures/crystal_hollows/lava_blaze",
					"quality":3,
					"weight":5000,
					"conditions":[
						{
							"condition":"location_check",
							"predicate":{
								"dimension":"skyblock:dwarven_mines"
							}
						}
					]
				},
				{
					"type":"loot_table",
					"name":"skyblock:items/sea_creatures/crystal_hollows/lava_pigman",
					"quality":3,
					"weight":5000,
					"conditions":[
						{
							"condition":"location_check",
							"predicate":{
								"dimension":"skyblock:dwarven_mines"
							}
						}
					]
				}
			]
		}
	]
}
