{
  "parent":"skyblock:collection/mining/coal/coal6",
  "display":{
    "icon":{
      "item":"minecraft:coal"
    },
    "title":"Coal VII",
    "description":"Mine 10,000 coal.",
    "frame":"task",
    "show_toast":true,
    "announce_to_chat":true,
    "hidden":false
  },
  "criteria":{
    "coal":{
      "trigger":"minecraft:item_durability_changed",
      "conditions":{
        "player":[
          {
            "condition": "minecraft:entity_properties",
            "entity": "this",
            "predicate": {
              "player":{
                "stats":[
                  {
                    "type":"minecraft:mined",
                    "stat":"minecraft:coal_ore",
                    "value":{
                      "min":10000
                    }
                  }
                ]
              }
            }
          }
        ]
      }
    }
  }
}
