{
  "type":"minecraft:entity",
  "pools":[
    {
      "rolls":1,
      "entries":[
        {
          "type":"minecraft:empty",
          "weight":22
        },
        {
          "type":"minecraft:item",
          "name":"minecraft:splash_potion",
          "weight":2,
          "functions":[
            {
              "function":"set_nbt",
              "tag":"{Potion:\"strong_healing\"}"
            }
          ]
        },
        {
          "type":"minecraft:item",
          "name":"minecraft:splash_potion",
          "weight":2,
          "functions":[
            {
              "function":"set_nbt",
              "tag":"{Potion:\"regeneration\"}"
            }
          ]
        },
        {
          "type":"minecraft:item",
          "name":"minecraft:potion",
          "weight":1,
          "functions":[
            {
              "function":"set_nbt",
              "tag":"{Potion:\"strong_swiftness\"}"
            }
          ]
        }
      ]
    }
  ]
}
