{
	"pools":[
		{
			"rolls":1,
			"entries":[
				{
					"type":"minecraft:item",
					"name":"minecraft:bone"
				}
			],
			"functions":[
				{
					"function":"set_count",
					"count":3
				},
				{
					"function":"looting_enchant",
					"count":{
						"min":0,
						"max":1
					}
				}
			]
		},
		{
			"rolls":1,
			"entries":[
				{
					"type":"minecraft:item",
					"name":"minecraft:coal"
				}
			],
			"functions":[
				{
					"function":"looting_enchant",
					"count":{
						"min":0,
						"max":1
					}
				}
			],
			"conditions":[
				{
					"condition":"minecraft:random_chance_with_looting",
					"chance":0.5,
					"looting_multiplier":0.01
				}
			]
		},
		{
			"rolls":1,
			"entries":[
				{
					"type":"minecraft:empty",
					"quality":-4,
					"weight":980
				},
				{
					"type":"minecraft:loot_table",
					"name":"skyblock:items/enchanted/coal",
					"quality":2,
					"weight":10
				},
				{
					"type":"minecraft:loot_table",
					"name":"skyblock:items/enchanted/charcoal",
					"quality":2,
					"weight":10
				}
			]
		},
		{
			"rolls":4,
			"entries":[
				{
					"type":"minecraft:loot_table",
					"name":"skyblock:gameplay/coins"
				}
			]
		}
	]
}
