{
  "pools":[
    {
      "rolls":1,
      "entries":[
        {
          "type":"item",
          "name":"stone_hoe",
          "functions":[
            {
              "function":"set_nbt",
              "tag":"{
                display:{
                  Name:\"{\\\"text\\\":\\\"Pythagorean Potato Hoe\\\",\\\"italic\\\":false,\\\"color\\\":\\\"white\\\"}\",
                  Lore:[
  									\"[\\\"\\\",{\\\"text\\\":\\\"Gain \\\",\\\"italic\\\":false,\\\"color\\\":\\\"gray\\\"},{\\\"text\\\":\\\"XP\\\",\\\"italic\\\":false,\\\"color\\\":\\\"aqua\\\"},{\\\"text\\\":\\\" from harvesting\\\",\\\"italic\\\":false,\\\"color\\\":\\\"gray\\\"}]\",
                    \"{\\\"text\\\":\\\"potatoes.\\\",\\\"italic\\\":false,\\\"color\\\":\\\"gray\\\"}\",
  									\"\\\" \\\"\",
  									\"[\\\"\\\",{\\\"text\\\":\\\"Harvest \\\",\\\"italic\\\":false,\\\"color\\\":\\\"gray\\\"},{\\\"text\\\":\\\"+10%\\\",\\\"italic\\\":false,\\\"color\\\":\\\"green\\\"},{\\\"text\\\":\\\" potatoes.\\\",\\\"italic\\\":false,\\\"color\\\":\\\"gray\\\"}]\",
  									\"\\\" \\\"\",
                    \"{\\\"text\\\":\\\"COMMON\\\",\\\"bold\\\":true,\\\"color\\\":\\\"white\\\"}\"
                  ]
                }
              }"
            }
          ]
        }
      ]
    }
  ]
}
