{
	"pools": [
		{
			"rolls": 1,
			"entries": [
				{
					"type": "item",
					"name": "minecraft:player_head",
					"functions": [
						{
							"function": "minecraft:set_nbt",
							"tag": "{
								SkullOwner:{Id:[I;-1805647051,-1086437079,-1897304066,1016911284],Properties:{textures:[{Value:\"eyJ0ZXh0dXJlcyI6eyJTS0lOIjp7InVybCI6Imh0dHA6Ly90ZXh0dXJlcy5taW5lY3JhZnQubmV0L3RleHR1cmUvYWY0MWNjMjI1MGQyZjVjZmNmNDM4NGFhMGNmM2UyM2MxOTc2NzU0OWEyYThhYmQ3NTMyYmQ1MmM1YTFkZSJ9fX0=\"}]}},
								display:{
									Name:\"{\\\"text\\\":\\\"Campfire Adept Badge\\\",\\\"italic\\\":false,\\\"color\\\":\\\"yellow\\\"}\",
									Lore:[
										\"[\\\"\\\",{\\\"text\\\":\\\"Grants permanent \\\",\\\"italic\\\":false,\\\"color\\\":\\\"gray\\\"},{\\\"text\\\":\\\"Fire Resistance.\\\",\\\"italic\\\":false,\\\"color\\\":\\\"#E49A3A\\\"},{\\\"text\\\":\\\".\\\",\\\"italic\\\":false,\\\"color\\\":\\\"gray\\\"}]\",
										\"[\\\"\\\",{\\\"text\\\":\\\"Heals \\\",\\\"italic\\\":false,\\\"color\\\":\\\"gray\\\"},{\\\"text\\\":\\\"4 Health\\\",\\\"italic\\\":false,\\\"color\\\":\\\"red\\\"},{\\\"text\\\":\\\" every \\\",\\\"italic\\\":false,\\\"color\\\":\\\"gray\\\"},{\\\"text\\\":\\\"2\\\",\\\"italic\\\":false,\\\"color\\\":\\\"green\\\"},{\\\"text\\\":\\\" seconds\\\",\\\"italic\\\":false,\\\"color\\\":\\\"gray\\\"}]\",
										\"[\\\"\\\",{\\\"text\\\":\\\"when on fire.\\\",\\\"italic\\\":false,\\\"color\\\":\\\"gray\\\"}]\",
										\"\\\" \\\"\"
										\"{\\\"text\\\":\\\"UNCOMMON\\\",\\\"bold\\\":true,\\\"color\\\":\\\"yellow\\\"}\"
									]
								}
							}"
						}
					]
				}
			]
		}
	]
}