{
	"pools":[
		{
			"rolls":1,
			"entries":[
				{
					"type":"alternatives",
					"children":[
						{
							"type":"item",
							"name":"minecraft:potion",
							"functions":[
								{
									"function":"minecraft:set_name",
									"name":{"text":"Dungeon V Potion","italic":false,"color":"aqua"}
								},
								{
									"function":"minecraft:set_lore",
									"lore":[
										{"text":"Regeneration III (40:00)","italic":false,"color":"blue"},
										{"text":"Strength IV (40:00)","italic":false,"color":"blue"},
										{"text":"Critical III (40:00)","italic":false,"color":"blue"},
										{"text":"Speed II (40:00)","italic":false,"color":"blue"},
										{"text":"Resistance IV (40:00)","italic":false,"color":"blue"},
										{"text":" "},
										{"text":"When Applied:","italic":false},
										{"text":"+12 Attack Damage","italic":false,"color":"blue"},
										{"text":"+40% Speed","italic":false,"color":"blue"},
										{"text":"+20% Crit Chance","italic":false,"color":"blue"},
										{"text":"+30% Crit Damage","italic":false,"color":"blue"},
										{"text":" "},
										{"text":"RARE","italic":true,"bold":true,"color":"aqua"}
									]
								},
								{
									"function":"minecraft:set_nbt",
									"tag":"{
										CustomPotionEffects:[
											{Id:10,Amplifier:2,Duration:48000},
											{Id:5,Amplifier:3,Duration:48000},
											{Id:1,Amplifier:1,Duration:48000},
											{Id:11,Amplifier:3,Duration:48000}
										],
										Potion:\"empty\",
										CustomPotionColor:1640667,
										HideFlags:32,
										Name:\"Dungeon V Potion\"
									}"
								}
							]
						}
					]
				}
			]
		}
	]
}

