{
	"pools":[
		{
			"rolls":1,
			"entries":[
				{
					"type":"item",
					"name":"minecraft:player_head",
					"functions":[
						{
							"function":"minecraft:set_name",
							"name":{"text":"Sludge Juice","italic":false,"color":"yellow"}
						},
						{
							"function":"minecraft:set_nbt",
							"tag":"{
								SkullOwner:{Id:[I;1253643186,-695120347,-1172774708,-883513824],Properties:{textures:[{Value:\"eyJ0ZXh0dXJlcyI6eyJTS0lOIjp7InVybCI6Imh0dHA6Ly90ZXh0dXJlcy5taW5lY3JhZnQubmV0L3RleHR1cmUvZTAxY2U2ODg0MjA3NGRkZTA1MzE4NWIyMThlMzRlZTMyNTljYjM2YWM0NzFkODA5OThmOWNiMDFmMzJlNTFjNyJ9fX0=\"}]}},
								Name:\"Sludge Juice\"
							}"
						}
					]
				}
			]
		}
	]
}

