{
	"pools":[
		{
			"rolls":1,
			"entries":[
				{
					"type":"minecraft:item",
					"name":"minecraft:iron_pickaxe",
					"functions":[
						{
							"function":"minecraft:set_name",
							"name":{"text":"Zombie Pickaxe","italic":false,"color":"white"}
						},
						{
							"function":"minecraft:set_lore",
							"lore":[
								{"text":" "},
								["",{"text":"Grants ","italic":false,"color":"gray"},{"text":"Haste II","italic":false,"color":"#D9C043"},{"text":" for ","italic":false,"color":"gray"},{"text":"5s","italic":false,"color":"green"},{"text":" after","italic":false,"color":"gray"}],
								["",{"text":"breaking Ores!","italic":false,"color":"gray"}],
								{"text":" "}
							]
						},
						{
							"function":"minecraft:set_nbt",
							"tag":"{
								Name:\"Zombie Pickaxe\",
								Rarity:0,
								Lore:[\"\",
									'{\"text\":\" \"}',
									'[\"\",{\"text\":\"Grants \",\"italic\":false,\"color\":\"gray\"},{\"text\":\"Haste II\",\"italic\":false,\"color\":\"#D9C043\"},{\"text\":\" for \",\"italic\":false,\"color\":\"gray\"},{\"text\":\"5s\",\"italic\":false,\"color\":\"green\"},{\"text\":\" after\",\"italic\":false,\"color\":\"gray\"}]',
									'[\"\",{\"text\":\"breaking Ores!\",\"italic\":false,\"color\":\"gray\"}]',
									'{\"text\":\" \"}'
								]
							}"
						,
						{
							"function":"minecraft:set_attributes",
							"modifiers":[
								{
									"name":"Attack Damage",
									"attribute":"generic.attack_damage",
									"operation":"addition",
									"amount":3,
									"slot":"mainhand"
								},
								{
									"name":"Attack Speed",
									"attribute":"generic.attack_speed",
									"operation":"addition",
									"amount":-2.8,
									"slot":"mainhand"
								}
							]
						}
					]
				}
			]
		}
	]
}

